TOPSIS_package/cli.py
TOPSIS_JagritiKhanna-0.1.0.dist-info/LICENSE.txt
TOPSIS_JagritiKhanna-0.1.0.dist-info/METADATA
TOPSIS_JagritiKhanna-0.1.0.dist-info/WHEEL
TOPSIS_JagritiKhanna-0.1.0.dist-info/entry_points.txt
TOPSIS_JagritiKhanna-0.1.0.dist-info/top_level.txt
TOPSIS_JagritiKhanna-0.1.0.dist-info/RECORD
