Metadata-Version: 2.1
Name: TOPSIS-JagritiKhanna
Version: 0.1.0
Summary: Topsis Analysis COE
Home-page: https://pypi.org/project/TOPSIS-JagritiKhanna
Author: Jagriti Khanna
Author-email: jagriti.khanna31@gmail.com
License: MIT
Platform: UNKNOWN
Classifier: License :: OSI Approved :: MIT License
Classifier: Programming Language :: Python :: 3
Classifier: Programming Language :: Python :: 3.7
Requires-Dist: numpy
Requires-Dist: pandas
